<?xml version="1.0" standalone="yes"?>
<MeterAssetCheckMeterConfigurationRequestMessage
	xmlns="http://www.emeter.com/energyip/amiinterface">
	<header>
		<verb>request</verb>
		<noun>CheckMeterConfiguration</noun>
		<revision>1</revision>
		<dateTime>2021-11-08T14:43:04.290+01:00</dateTime>
		<source>EIP</source>
		<messageID>523</messageID>
	</header>
	<payload>
		<meterAsset>
			<mRID>SAG1030000045065</mRID>
			<idType>METER_X_ELECTRONIC_ID</idType>
			<parameter>
				<name>profileName</name>
				<value>ReadBreakerStatus</value>
			</parameter>
		</meterAsset>
		<executeStartTime>2021-11-08T14:41:48.000+01:00</executeStartTime>
		<executeExpireTime>2030-11-08T15:11:48.000+01:00</executeExpireTime>
	</payload>
</MeterAssetCheckMeterConfigurationRequestMessage>
